bravo_py-0.1.0.dist-info/licenses/LICENSE
pybravo/__init__.py
pybravo/core.py
pybravo/exceptions.py
bravo_py-0.1.0.dist-info/METADATA
bravo_py-0.1.0.dist-info/WHEEL
bravo_py-0.1.0.dist-info/top_level.txt
bravo_py-0.1.0.dist-info/RECORD
