Metadata-Version: 2.4
Name: bravo-py
Version: 0.1.0
Summary: Python driver with lower level control to Bravo liquid handler
Author-email: Silvio Ortiz <clvoaburto@gmail.com>
Project-URL: Homepage, https://github.com/SilvioAburto/pybravo
Classifier: Programming Language :: Python :: 3
Classifier: License :: OSI Approved :: MIT License
Classifier: Operating System :: OS Independent
Requires-Python: >=3.9
License-File: LICENSE
Requires-Dist: requests
Dynamic: license-file
